{
  "pattern_en": "I'm sorry for",
  "pattern_kr": "~해서 미안해",
  "pattern_highlight": "I'm sorry for",
  "sentences": [
    { "en": "I'm sorry for being late", "kr": "늦어서 미안해", "pron": "아임 쏘리 포 비잉 레이트", "keyword": "late 늦은" },
    { "en": "I'm sorry for the trouble", "kr": "번거롭게 해서 미안해", "pron": "아임 쏘리 포 더 트러블", "keyword": "trouble 문제/번거로움" },
    { "en": "I'm sorry for interrupting", "kr": "말 끊어서 미안해", "pron": "아임 쏘리 포 인터럽팅", "keyword": "interrupt 방해하다" },
    { "en": "I'm sorry for saying that", "kr": "그렇게 말해서 미안해", "pron": "아임 쏘리 포 세잉 댓", "keyword": "say 말하다" },
    { "en": "I'm sorry for the mistake", "kr": "실수해서 미안해", "pron": "아임 쏘리 포 더 미스테이크", "keyword": "mistake 실수" },
    { "en": "I'm sorry for keeping you waiting", "kr": "기다리게 해서 미안해", "pron": "아임 쏘리 포 키핑 유 웨이팅", "keyword": "wait 기다리다" },
    { "en": "I'm sorry for my behavior", "kr": "내가 그렇게 행동해서 미안해", "pron": "아임 쏘리 포 마이 비헤이비어", "keyword": "behavior 행동" },
    { "en": "I'm sorry for forgetting your birthday", "kr": "생일 깜빡해서 미안해", "pron": "아임 쏘리 포 포게팅 유어 버스데이", "keyword": "forget 잊다" },
    { "en": "I'm sorry for the confusion", "kr": "혼란을 줘서 미안해", "pron": "아임 쏘리 포 더 컨퓨전", "keyword": "confusion 혼란" },
    { "en": "I'm sorry for not calling back", "kr": "전화 못 해서 미안해", "pron": "아임 쏘리 포 낫 콜링 백", "keyword": "call 전화하다" },
    { "en": "I'm sorry for being so sensitive", "kr": "너무 예민하게 굴어서 미안해", "pron": "아임 쏘리 포 비잉 쏘 센시티브", "keyword": "sensitive 예민한" },
    { "en": "I'm sorry for all the stress", "kr": "스트레스 줘서 미안해", "pron": "아임 쏘리 포 올 더 스트레스", "keyword": "stress 스트레스" },
    { "en": "I'm sorry for making a mess", "kr": "어질러놔서 미안해", "pron": "아임 쏘리 포 메이킹 어 메스", "keyword": "mess 엉망" },
    { "en": "I'm sorry for not listening", "kr": "안 들어서 미안해", "pron": "아임 쏘리 포 낫 리스닝", "keyword": "listen 듣다" },
    { "en": "I'm sorry for the sudden change", "kr": "갑작스러운 변경이라 미안해", "pron": "아임 쏘리 포 더 서든 체인지", "keyword": "sudden 갑작스러운" },
    { "en": "I'm sorry for losing your book", "kr": "네 책 잃어버려서 미안해", "pron": "아임 쏘리 포 루징 유어 북", "keyword": "lose 잃어버리다" },
    { "en": "I'm sorry for my tone", "kr": "내 말투가 거칠어서 미안해", "pron": "아임 쏘리 포 마이 톤", "keyword": "tone 말투" },
    { "en": "I'm sorry for waking you up", "kr": "깨워서 미안해", "pron": "아임 쏘리 포 웨이킹 유 업", "keyword": "wake 깨우다" },
    { "en": "I'm sorry for being difficult", "kr": "까다롭게 굴어서 미안해", "pron": "아임 쏘리 포 비잉 디피컬트", "keyword": "difficult 까다로운" },
    { "en": "I'm sorry for not being there", "kr": "옆에 있어주지 못해서 미안해", "pron": "아임 쏘리 포 낫 비잉 데어", "keyword": "there 그곳에" },
    { "en": "I'm sorry for the long wait", "kr": "오래 기다리게 해서 미안해", "pron": "아임 쏘리 포 더 롱 웨이트", "keyword": "wait 기다림" },
    { "en": "I'm sorry for my lack of planning", "kr": "계획을 제대로 세우지 못해서 미안해", "pron": "아임 쏘리 포 마이 랙 오브 플래닝", "keyword": "lack 부족" },
    { "en": "I'm sorry for the damage", "kr": "피해를 줘서 미안해", "pron": "아임 쏘리 포 더 대미지", "keyword": "damage 피해" },
    { "en": "I'm sorry for not telling you", "kr": "말 안 해줘서 미안해", "pron": "아임 쏘리 포 낫 텔링 유", "keyword": "tell 말하다" },
    { "en": "I'm sorry for the misunderstanding", "kr": "오해를 불러일으켜 미안해", "pron": "아임 쏘리 포 더 미스언더스탠딩", "keyword": "misunderstanding 오해" },
    { "en": "I'm sorry for being selfish", "kr": "이기적이어서 미안해", "pron": "아임 쏘리 포 비잉 셀피쉬", "keyword": "selfish 이기적인" },
    { "en": "I'm sorry for all the noise", "kr": "너무 시끄럽게 해서 미안해", "pron": "아임 쏘리 포 올 더 노이즈", "keyword": "noise 소음" },
    { "en": "I'm sorry for missing the meeting", "kr": "회의 빠져서 미안해", "pron": "아임 쏘리 포 미싱 더 미팅", "keyword": "miss 빠지다" },
    { "en": "I'm sorry for being so blunt", "kr": "너무 직설적이어서 미안해", "pron": "아임 쏘리 포 비잉 쏘 블런트", "keyword": "blunt 직설적인" },
    { "en": "I'm sorry for the late response", "kr": "답장이 늦어서 미안해", "pron": "아임 쏘리 포 더 레이트 리스폰스", "keyword": "response 답변" }
  ]
}